{
  "source": "option_9gamepad2_assign.pbd",
  "hotspots": [
    {
      "layer_id": "helpbase",
      "sort_index": 1154,
      "height": 34,
      "ch": 94
    },
    {
      "layer_id": "base",
      "sort_index": 1235,
      "height": 235,
      "storagex": 52
    },
    {
      "layer_id": "copy",
      "sort_index": 1890,
      "height": 83
    },
    {
      "layer_id": "button_r3",
      "sort_index": 1936,
      "height": 192,
      "ch": 59
    },
    {
      "layer_id": "button_x",
      "sort_index": 2088,
      "height": 92,
      "ch": 3
    },
    {
      "layer_id": "button_a",
      "sort_index": 2135,
      "height": 68,
      "ch": 57
    },
    {
      "layer_id": "button_b",
      "sort_index": 2160,
      "height": 126,
      "ch": 71
    },
    {
      "layer_id": "layer",
      "sort_index": 2247,
      "height": 68
    },
    {
      "layer_id": "button_r2",
      "sort_index": 2344,
      "height": 252,
      "ch": 6
    },
    {
      "layer_id": "button_start",
      "sort_index": 2349,
      "ch": 207
    },
    {
      "layer_id": "button_l1",
      "sort_index": 2398,
      "height": 107,
      "ch": 111
    },
    {
      "layer_id": "button_r1",
      "sort_index": 2485,
      "height": 65,
      "ch": 189
    },
    {
      "layer_id": "button_l2",
      "sort_index": 2519,
      "height": 145,
      "ch": 56
    },
    {
      "layer_id": "button_l3",
      "sort_index": 2548,
      "height": 156,
      "ch": 17
    },
    {
      "layer_id": "option_9gamepad__pack",
      "sort_index": 3098,
      "width": 181
    },
    {
      "layer_id": "button_select",
      "sort_index": 3165,
      "ch": 81
    },
    {
      "layer_id": "button_y",
      "sort_index": 3539,
      "height": 47,
      "ch": 165
    },
    {
      "layer_id": "option_9gamepad2_assign__pack",
      "sort_index": 5508,
      "width": 241
    },
    {
      "layer_id": "back",
      "sort_index": null,
      "width": 242,
      "height": 83
    },
    {
      "layer_id": "caption",
      "sort_index": null,
      "height": 42,
      "ch": 180
    },
    {
      "layer_id": "cr",
      "sort_index": null,
      "cw": 155
    },
    {
      "layer_id": "f",
      "sort_index": null,
      "x": 148,
      "width": 252
    },
    {
      "layer_id": "false",
      "sort_index": null,
      "width": 31
    },
    {
      "layer_id": "front",
      "sort_index": null,
      "ch": 28
    },
    {
      "layer_id": "gamepad",
      "sort_index": null,
      "height": 215,
      "ch": 28
    },
    {
      "layer_id": "holdimage",
      "sort_index": null,
      "height": 215
    },
    {
      "layer_id": "imports",
      "sort_index": null,
      "height": 215
    },
    {
      "layer_id": "j",
      "sort_index": null,
      "cy": 186
    },
    {
      "layer_id": "names",
      "sort_index": null,
      "height": 215
    },
    {
      "layer_id": "option_9gamepad",
      "sort_index": null,
      "height": 215
    },
    {
      "layer_id": "option__bg0",
      "sort_index": null,
      "storagex": 52
    },
    {
      "layer_id": "option__pack",
      "sort_index": null,
      "height": 215,
      "width": 148
    },
    {
      "layer_id": "radio",
      "sort_index": null,
      "height": 236
    },
    {
      "layer_id": "storagex",
      "sort_index": null,
      "storagey": 104
    },
    {
      "layer_id": "storagey",
      "sort_index": null,
      "height": 235
    },
    {
      "layer_id": "title",
      "sort_index": null,
      "width": 237,
      "height": 94
    },
    {
      "layer_id": "top",
      "sort_index": null,
      "ch": 28
    },
    {
      "layer_id": "width",
      "sort_index": null,
      "x": 242
    },
    {
      "layer_id": "x",
      "sort_index": null,
      "y": 223
    },
    {
      "layer_id": "y",
      "sort_index": null,
      "height": 83
    }
  ],
  "bindings": []
}